maser/plot/__init__.py
maser/plot/base/__init__.py
maser/plot/base/base.py
maser/plot/base/dataset_filename_regex.json
maser/plot/cdpp/__init__.py
maser/plot/cdpp/interball/__init__.py
maser/plot/cdpp/interball/plot.py
maser/plot/cdpp/stereo/__init__.py
maser/plot/cdpp/stereo/plot.py
maser/plot/cdpp/viking/__init__.py
maser/plot/cdpp/viking/plot.py
maser/plot/cdpp/wind/__init__.py
maser/plot/cdpp/wind/plot.py
maser/plot/ecallisto/__init__.py
maser/plot/ecallisto/plot.py
maser/plot/nancay/__init__.py
maser/plot/nancay/nda/__init__.py
maser/plot/nancay/nda/plot.py
maser/plot/nancay/nenufar/__init__.py
maser/plot/nancay/nenufar/plot.py
maser/plot/padc/__init__.py
maser/plot/padc/bepi/__init__.py
maser/plot/padc/bepi/sorbet/__init__.py
maser/plot/padc/bepi/sorbet/plot.py
maser/plot/padc/cassini/__init__.py
maser/plot/padc/cassini/plot.py
maser/plot/padc/expres/__init__.py
maser/plot/padc/expres/plot.py
maser/plot/padc/juno/__init__.py
maser/plot/padc/juno/plot.py
maser/plot/padc/stereo/__init__.py
maser/plot/padc/stereo/plot.py
maser/plot/padc/wind/__init__.py
maser/plot/padc/wind/plot.py
maser/plot/pds/__init__.py
maser/plot/pds/co/__init__.py
maser/plot/pds/co/plot.py
maser/plot/pds/plot.py
maser/plot/pds/vg/__init__.py
maser/plot/pds/vg/plot.py
maser/plot/psa/__init__.py
maser/plot/psa/mex/__init__.py
maser/plot/psa/mex/plot.py
maser/plot/rpw/__init__.py
maser/plot/rpw/cross_section.py
maser/plot/rpw/lfr.py
maser/plot/rpw/plot.py
maser/plot/rpw/plot_mean.py
maser/plot/rpw/quick_look.py
maser/plot/rpw/tnr.py
maser_plot-0.4.0.dist-info/METADATA
maser_plot-0.4.0.dist-info/WHEEL
maser_plot-0.4.0.dist-info/RECORD
