Metadata-Version: 2.3
Name: maser-plot
Version: 0.4.0
Summary: Maser4py submodule to plot radio data
License: CECILL-B
Author: MASER team
Author-email: contact.maser@obspm.fr
Requires-Python: >=3.9,<4
Classifier: License :: CeCILL-B Free Software License Agreement (CECILL-B)
Classifier: Programming Language :: Python :: 3
Classifier: Programming Language :: Python :: 3.9
Classifier: Programming Language :: Python :: 3.10
Classifier: Programming Language :: Python :: 3.11
Classifier: Programming Language :: Python :: 3.12
Classifier: Programming Language :: Python :: 3.13
Requires-Dist: matplotlib (>=3.5,<4)
